[{"id":"e2","title":"City Hunt: Web Dev Edition!!!!!!","description":"Explore the city and discover hidden gems while completing fun web development challenges.","date":"2024-10-07","time":"10:00","location":"Tech Training Academy, Los Angeles, CA","image":"buzzing-city.jpg"},{"id":"e3","title":"Women in Web Development Mixer!!!???!!!","description":"An empowering event dedicated to women who are passionate about web development. Connect, share, and inspire.","date":"2024-05-21","time":"16:30","location":"Empowerment Hall, Seattle, WA","image":"women-coding.jpg"},{"id":"e4","title":"Beginner's Guide to HTML & CSS","description":"Dive into the world of HTML and CSS. This workshop is perfect for those taking their first steps in web development.","date":"2023-11-03","time":"18:30","location":"Learning Labs, Austin, TX","image":"laptop-on-desk.jpg"},{"id":"7356","title":"test event","description":"this is a test event","date":"2024-01-03","time":"18:50","location":"ny","image":"park.jpg"},{"id":"5228","title":"test","description":"test test","date":"2024-01-06","time":"18:00","location":"ny","image":"park.jpg"},{"id":"6456","title":"test","description":"test","date":"2024-01-01","time":"17:00","location":"ny","image":"park.jpg"},{"id":"7429","title":"dddd","description":"aaa","date":"2024-01-01","time":"16:00","location":"ny","image":"park.jpg"}]